{
  "name": "surya_cep",
  "nodes": [
    {
      "parameters": {
        "jsCode": "// Extrai o CEP dos argumentos\nconst cep = $input.first().json.cep;\n\n// Remove todos os caracteres não numéricos\nconst cepNumerico = cep.replace(/\\D/g, '');\n\n// Retorna valor formatado\nreturn [{\n  cep: cepNumerico || null\n}];"
      },
      "type": "n8n-nodes-base.code",
      "typeVersion": 2,
      "position": [
        192,
        0
      ],
      "id": "75b16025-8044-45bf-af86-da9e4465e7b2",
      "name": "Code"
    },
    {
      "parameters": {
        "url": "=https://viacep.com.br/ws/{{ $json.cep }}/json/",
        "options": {}
      },
      "type": "n8n-nodes-base.httpRequest",
      "typeVersion": 4.2,
      "position": [
        368,
        0
      ],
      "id": "518c1662-b056-4123-bc80-5c27b7587430",
      "name": "HTTP Request"
    },
    {
      "parameters": {
        "workflowInputs": {
          "values": [
            {
              "name": "sessionid"
            },
            {
              "name": "cep"
            },
            {
              "name": "data"
            }
          ]
        }
      },
      "type": "n8n-nodes-base.executeWorkflowTrigger",
      "typeVersion": 1.1,
      "position": [
        0,
        0
      ],
      "id": "eb1427be-7b97-4300-affb-77ed6d503390",
      "name": "Workflow_cep"
    },
    {
      "parameters": {
        "operation": "update",
        "schema": {
          "__rl": true,
          "mode": "list",
          "value": "public"
        },
        "table": {
          "__rl": true,
          "value": "dados_cliente",
          "mode": "list",
          "cachedResultName": "dados_cliente"
        },
        "columns": {
          "mappingMode": "defineBelow",
          "value": {
            "sessionid": "={{ $('Workflow_cep').item.json.sessionid }}",
            "cep": "={{ $json.cep }}",
            "logradouro": "={{ $json.logradouro }}",
            "complemento": "={{ $json.complemento }}",
            "unidade": "={{ $json.unidade }}",
            "bairro": "={{ $json.bairro }}",
            "localidade": "={{ $json.localidade }}",
            "uf": "={{ $json.uf }}"
          },
          "matchingColumns": [
            "sessionid"
          ],
          "schema": [
            {
              "id": "id",
              "displayName": "id",
              "required": false,
              "defaultMatch": true,
              "display": true,
              "type": "number",
              "canBeUsedToMatch": true,
              "removed": true
            },
            {
              "id": "created_at",
              "displayName": "created_at",
              "required": false,
              "defaultMatch": false,
              "display": true,
              "type": "string",
              "canBeUsedToMatch": true,
              "removed": true
            },
            {
              "id": "telefone",
              "displayName": "telefone",
              "required": false,
              "defaultMatch": false,
              "display": true,
              "type": "string",
              "canBeUsedToMatch": true,
              "removed": true
            },
            {
              "id": "sessionid",
              "displayName": "sessionid",
              "required": false,
              "defaultMatch": false,
              "display": true,
              "type": "string",
              "canBeUsedToMatch": true,
              "removed": false
            },
            {
              "id": "nome",
              "displayName": "nome",
              "required": false,
              "defaultMatch": false,
              "display": true,
              "type": "string",
              "canBeUsedToMatch": true,
              "removed": true
            },
            {
              "id": "consumo",
              "displayName": "consumo",
              "required": false,
              "defaultMatch": false,
              "display": true,
              "type": "string",
              "canBeUsedToMatch": true,
              "removed": true
            },
            {
              "id": "cep",
              "displayName": "cep",
              "required": false,
              "defaultMatch": false,
              "display": true,
              "type": "string",
              "canBeUsedToMatch": true
            },
            {
              "id": "logradouro",
              "displayName": "logradouro",
              "required": false,
              "defaultMatch": false,
              "display": true,
              "type": "string",
              "canBeUsedToMatch": true
            },
            {
              "id": "complemento",
              "displayName": "complemento",
              "required": false,
              "defaultMatch": false,
              "display": true,
              "type": "string",
              "canBeUsedToMatch": true
            },
            {
              "id": "unidade",
              "displayName": "unidade",
              "required": false,
              "defaultMatch": false,
              "display": true,
              "type": "string",
              "canBeUsedToMatch": true
            },
            {
              "id": "bairro",
              "displayName": "bairro",
              "required": false,
              "defaultMatch": false,
              "display": true,
              "type": "string",
              "canBeUsedToMatch": true
            },
            {
              "id": "localidade",
              "displayName": "localidade",
              "required": false,
              "defaultMatch": false,
              "display": true,
              "type": "string",
              "canBeUsedToMatch": true
            },
            {
              "id": "uf",
              "displayName": "uf",
              "required": false,
              "defaultMatch": false,
              "display": true,
              "type": "string",
              "canBeUsedToMatch": true
            },
            {
              "id": "ai_agente",
              "displayName": "ai_agente",
              "required": false,
              "defaultMatch": false,
              "display": true,
              "type": "string",
              "canBeUsedToMatch": true,
              "removed": true
            },
            {
              "id": "telhado",
              "displayName": "telhado",
              "required": false,
              "defaultMatch": false,
              "display": true,
              "type": "string",
              "canBeUsedToMatch": true,
              "removed": true
            },
            {
              "id": "email",
              "displayName": "email",
              "required": false,
              "defaultMatch": false,
              "display": true,
              "type": "string",
              "canBeUsedToMatch": true,
              "removed": true
            },
            {
              "id": "tipo_pagamento",
              "displayName": "tipo_pagamento",
              "required": false,
              "defaultMatch": false,
              "display": true,
              "type": "string",
              "canBeUsedToMatch": true,
              "removed": true
            },
            {
              "id": "valor_esperado",
              "displayName": "valor_esperado",
              "required": false,
              "defaultMatch": false,
              "display": true,
              "type": "string",
              "canBeUsedToMatch": true,
              "removed": true
            },
            {
              "id": "cpf",
              "displayName": "cpf",
              "required": false,
              "defaultMatch": false,
              "display": true,
              "type": "string",
              "canBeUsedToMatch": true,
              "removed": true
            },
            {
              "id": "data_nascimento",
              "displayName": "data_nascimento",
              "required": false,
              "defaultMatch": false,
              "display": true,
              "type": "string",
              "canBeUsedToMatch": true,
              "removed": true
            },
            {
              "id": "parcelas",
              "displayName": "parcelas",
              "required": false,
              "defaultMatch": false,
              "display": true,
              "type": "string",
              "canBeUsedToMatch": true,
              "removed": true
            },
            {
              "id": "ultimo_contato",
              "displayName": "ultimo_contato",
              "required": false,
              "defaultMatch": false,
              "display": true,
              "type": "dateTime",
              "canBeUsedToMatch": true,
              "removed": true
            },
            {
              "id": "tipo_consumo",
              "displayName": "tipo_consumo",
              "required": false,
              "defaultMatch": false,
              "display": true,
              "type": "string",
              "canBeUsedToMatch": true,
              "removed": true
            }
          ],
          "attemptToConvertTypes": false,
          "convertFieldsToString": false
        },
        "options": {}
      },
      "type": "n8n-nodes-base.postgres",
      "typeVersion": 2.6,
      "position": [
        544,
        0
      ],
      "id": "e3a521b4-6232-483f-8e60-b3c7ea20144a",
      "name": "Postgres",
      "credentials": {
        "postgres": {
          "id": "nNVFJrttrkWb8cxD",
          "name": "Postgres account"
        }
      }
    }
  ],
  "pinData": {},
  "connections": {
    "Code": {
      "main": [
        [
          {
            "node": "HTTP Request",
            "type": "main",
            "index": 0
          }
        ]
      ]
    },
    "HTTP Request": {
      "main": [
        [
          {
            "node": "Postgres",
            "type": "main",
            "index": 0
          }
        ]
      ]
    },
    "Workflow_cep": {
      "main": [
        [
          {
            "node": "Code",
            "type": "main",
            "index": 0
          }
        ]
      ]
    }
  },
  "active": true,
  "settings": {
    "executionOrder": "v1"
  },
  "versionId": "92d7fb71-6be1-420c-8af4-9343522c3512",
  "meta": {
    "templateCredsSetupCompleted": true,
    "instanceId": "9de78f2ac9841d2abe9d4cbd4388e0b66ff29866a2e1eee2161f034fbbf93eeb"
  },
  "id": "2SEAmNnyrnl2YXJA",
  "tags": [
    {
      "updatedAt": "2025-12-14T02:34:59.320Z",
      "createdAt": "2025-12-14T02:34:59.320Z",
      "id": "nx90BLPdsXGI455N",
      "name": "SUSTENTO"
    }
  ]
}